eaf/__init__.py
eaf/eaf.py
eaf/plot_surface.py
eaf/utils.py
empirical_attainment_func-0.4.3.dist-info/LICENSE
empirical_attainment_func-0.4.3.dist-info/METADATA
empirical_attainment_func-0.4.3.dist-info/WHEEL
empirical_attainment_func-0.4.3.dist-info/top_level.txt
empirical_attainment_func-0.4.3.dist-info/RECORD
