Metadata-Version: 2.1
Name: empirical-attainment-func
Version: 0.4.3
Home-page: https://github.com/nabenabe0928/empirical-attainment-func
Author: nabenabe0928
Author-email: shuhei.watanabe.utokyo@gmail.com
Platform: Linux
Requires-Python: >=3.8
License-File: LICENSE
Requires-Dist: fast-pareto
Requires-Dist: matplotlib
Requires-Dist: pytest-cov
Requires-Dist: pytest
Requires-Dist: flake8
Requires-Dist: black
Requires-Dist: mypy
